directed_edge.py
setup.py
edge.egg-info/PKG-INFO
edge.egg-info/SOURCES.txt
edge.egg-info/dependency_links.txt
edge.egg-info/requires.txt
edge.egg-info/top_level.txt