Metadata-Version: 1.0
Name: edge
Version: 0.3.2
Summary: Python bindings for Directed Edge's API
Home-page: http://pypi.python.org/pypi/edge
Author: Directed Edge
Author-email: UNKNOWN
License: BSD
Platform: UNKNOWN
